README.txt
setup.cfg
setup.py
ro/__init__.py
ro.bdb.cmmi.egg-info/PKG-INFO
ro.bdb.cmmi.egg-info/SOURCES.txt
ro.bdb.cmmi.egg-info/dependency_links.txt
ro.bdb.cmmi.egg-info/entry_points.txt
ro.bdb.cmmi.egg-info/namespace_packages.txt
ro.bdb.cmmi.egg-info/requires.txt
ro.bdb.cmmi.egg-info/top_level.txt
ro.bdb.cmmi.egg-info/zip-safe
ro/bdb/__init__.py
ro/bdb/cmmi/__init__.py
ro/bdb/cmmi/tests.py