Metadata-Version: 1.0
Name: ro.bdb.cmmi
Version: 1.0.4
Summary: ZC Buildout recipe for BDB configure/make/make install
Home-page: http://www.python.org/pypi/ro.bdb.cmmi
Author: Reed O'Brien
Author-email: reed@koansys.com
License: ZPL 2.1
Keywords: zope3
Platform: UNKNOWN
